glworia/__init__.py
glworia/amp/__init__.py
glworia/amp/amplification_factor.py
glworia/amp/contour.py
glworia/amp/frequency_domain.py
glworia/amp/interpolate.py
glworia/amp/lens_functions.py
glworia/amp/lens_model.py
glworia/amp/load_interp.py
glworia/amp/plot.py
glworia/amp/root.py
glworia/amp/utils.py
glworia/pe/__init__.py
glworia/pe/prior.py
glworia/pe/waveform.py
glworia-0.0.0.dist-info/METADATA
glworia-0.0.0.dist-info/WHEEL
glworia-0.0.0.dist-info/licenses/LICENSE
glworia-0.0.0.dist-info/RECORD
