Metadata-Version: 2.3
Name: glworia
Version: 0.0.0
Summary: A package for wave-optics lensing calculations
Project-URL: Homepage, https://github.com/mhycheung/glworia
Project-URL: Bug Tracker, https://github.com/mhycheung/glworia/issues
Author-email: Mark Ho-Yeuk Cheung <hcheung5@jhu.edu>
License-File: LICENSE
Classifier: License :: OSI Approved :: MIT License
Classifier: Operating System :: OS Independent
Classifier: Programming Language :: Python :: 3.8
Classifier: Programming Language :: Python :: 3.9
Classifier: Programming Language :: Python :: 3.10
Classifier: Programming Language :: Python :: 3.11
Requires-Python: <3.12,>=3.8
Requires-Dist: jax>0.3.23
Requires-Dist: jaxlib>0.3.23
Requires-Dist: matplotlib>3.6.1
Requires-Dist: numpy>1.23
Requires-Dist: scipy>1.9.3
Requires-Dist: tqdm>4.61.1
